iso2web.py
iso2web-1.0.3.dist-info/METADATA
iso2web-1.0.3.dist-info/WHEEL
iso2web-1.0.3.dist-info/entry_points.txt
iso2web-1.0.3.dist-info/top_level.txt
iso2web-1.0.3.dist-info/RECORD
