Metadata-Version: 2.2
Name: iso2web
Version: 1.0.3
Summary: Tool to Send Proofpoint Isolation Data to a Webhook
License: MIT
Project-URL: repository, https://github.com/pfptcommunity/iso2web
Project-URL: homepage, https://www.proofpoint.com/us/products/cloud-security/isolation
Project-URL: documentation, https://proofpoint.my.site.com/community/s/article/Proofpoint-Isolation-API-Guide
Requires-Python: >3.9
Requires-Dist: python-dateutil
Requires-Dist: requests
Requires-Dist: cryptography
Requires-Dist: pysocks
